fastapi_csv_downloader/__init__.py
fastapi_csv_downloader/csv_exporter.py
fastapi_csv_downloader-1.0.0.dist-info/METADATA
fastapi_csv_downloader-1.0.0.dist-info/WHEEL
fastapi_csv_downloader-1.0.0.dist-info/top_level.txt
fastapi_csv_downloader-1.0.0.dist-info/RECORD
