Metadata-Version: 2.4
Name: fastapi-csv-downloader
Version: 1.0.0
Summary: CSV download utility for FastAPI
Home-page: https://github.com/AnisurRahman06046/fastapi-csv-downloader
Author: Md Anisur Rahman
Classifier: Programming Language :: Python :: 3
Classifier: Framework :: FastAPI
Classifier: License :: OSI Approved :: MIT License
Requires-Python: >=3.7
Requires-Dist: fastapi
Dynamic: author
Dynamic: classifier
Dynamic: description
Dynamic: description-content-type
Dynamic: home-page
Dynamic: requires-dist
Dynamic: requires-python
Dynamic: summary
